GuessNumberAndLetter
