Metadata-Version: 1.0
Name: GuessNumberLetter
Version: 0.3
Summary: Example Game of Object Oriented Programming in Python
Home-page: https://github.com/giovanib02/Guess-number
Author: Carlos Barillas
Author-email: giovanib07@gmail.com
License: UNKNOWN
Platform: UNKNOWN
